{
  "E06000001": { "la_name":"Hartlepool", "region_code":"E12000001", "region_name":"North East"},
  "E06000002": { "la_name":"Middlesbrough", "region_code":"E12000001", "region_name":"North East"},
  "E06000003": { "la_name":"Redcar and Cleveland", "region_code":"E12000001", "region_name":"North East"},
  "E06000004": { "la_name":"Stockton-on-Tees", "region_code":"E12000001", "region_name":"North East"},
  "E06000005": { "la_name":"Darlington", "region_code":"E12000001", "region_name":"North East"},
  "E06000006": { "la_name":"Halton", "region_code":"E12000002", "region_name":"North West"},
  "E06000007": { "la_name":"Warrington", "region_code":"E12000002", "region_name":"North West"},
  "E06000008": { "la_name":"Blackburn with Darwen", "region_code":"E12000002", "region_name":"North West"},
  "E06000009": { "la_name":"Blackpool", "region_code":"E12000002", "region_name":"North West"},
  "E06000010": { "la_name":"Kingston upon Hull, City of", "region_code":"E12000003", "region_name":"Yorkshire and The Humber"},
  "E06000011": { "la_name":"East Riding of Yorkshire", "region_code":"E12000003", "region_name":"Yorkshire and The Humber"},
  "E06000012": { "la_name":"North East Lincolnshire", "region_code":"E12000003", "region_name":"Yorkshire and The Humber"},
  "E06000013": { "la_name":"North Lincolnshire", "region_code":"E12000003", "region_name":"Yorkshire and The Humber"},
  "E06000014": { "la_name":"York", "region_code":"E12000003", "region_name":"Yorkshire and The Humber"},
  "E06000015": { "la_name":"Derby", "region_code":"E12000004", "region_name":"East Midlands"},
  "E06000016": { "la_name":"Leicester", "region_code":"E12000004", "region_name":"East Midlands"},
  "E06000017": { "la_name":"Rutland", "region_code":"E12000004", "region_name":"East Midlands"},
  "E06000018": { "la_name":"Nottingham", "region_code":"E12000004", "region_name":"East Midlands"},
  "E06000019": { "la_name":"Herefordshire, County of", "region_code":"E12000005", "region_name":"West Midlands"},
  "E06000020": { "la_name":"Telford and Wrekin", "region_code":"E12000005", "region_name":"West Midlands"},
  "E06000021": { "la_name":"Stoke-on-Trent", "region_code":"E12000005", "region_name":"West Midlands"},
  "E06000022": { "la_name":"Bath and North East Somerset", "region_code":"E12000009", "region_name":"South West"},
  "E06000023": { "la_name":"Bristol, City of", "region_code":"E12000009", "region_name":"South West"},
  "E06000024": { "la_name":"North Somerset", "region_code":"E12000009", "region_name":"South West"},
  "E06000025": { "la_name":"South Gloucestershire", "region_code":"E12000009", "region_name":"South West"},
  "E06000026": { "la_name":"Plymouth", "region_code":"E12000009", "region_name":"South West"},
  "E06000027": { "la_name":"Torbay", "region_code":"E12000009", "region_name":"South West"},
  "E06000028": { "la_name":"Bournemouth", "region_code":"E12000009", "region_name":"South West"},
  "E06000029": { "la_name":"Poole", "region_code":"E12000009", "region_name":"South West"},
  "E06000030": { "la_name":"Swindon", "region_code":"E12000009", "region_name":"South West"},
  "E06000031": { "la_name":"Peterborough", "region_code":"E12000006", "region_name":"East"},
  "E06000032": { "la_name":"Luton", "region_code":"E12000006", "region_name":"East"},
  "E06000033": { "la_name":"Southend-on-Sea", "region_code":"E12000006", "region_name":"East"},
  "E06000034": { "la_name":"Thurrock", "region_code":"E12000006", "region_name":"East"},
  "E06000035": { "la_name":"Medway", "region_code":"E12000008", "region_name":"South East"},
  "E06000036": { "la_name":"Bracknell Forest", "region_code":"E12000008", "region_name":"South East"},
  "E06000037": { "la_name":"West Berkshire", "region_code":"E12000008", "region_name":"South East"},
  "E06000038": { "la_name":"Reading", "region_code":"E12000008", "region_name":"South East"},
  "E06000039": { "la_name":"Slough", "region_code":"E12000008", "region_name":"South East"},
  "E06000040": { "la_name":"Windsor and Maidenhead", "region_code":"E12000008", "region_name":"South East"},
  "E06000041": { "la_name":"Wokingham", "region_code":"E12000008", "region_name":"South East"},
  "E06000042": { "la_name":"Milton Keynes", "region_code":"E12000008", "region_name":"South East"},
  "E06000043": { "la_name":"Brighton and Hove", "region_code":"E12000008", "region_name":"South East"},
  "E06000044": { "la_name":"Portsmouth", "region_code":"E12000008", "region_name":"South East"},
  "E06000045": { "la_name":"Southampton", "region_code":"E12000008", "region_name":"South East"},
  "E06000046": { "la_name":"Isle of Wight", "region_code":"E12000008", "region_name":"South East"},
  "E06000047": { "la_name":"County Durham", "region_code":"E12000001", "region_name":"North East"},
  "E06000048": { "la_name":"Northumberland", "region_code":"E12000001", "region_name":"North East"},
  "E06000057": { "la_name":"Northumberland", "region_code":"E12000001", "region_name":"North East"},
  "E06000049": { "la_name":"Cheshire East", "region_code":"E12000002", "region_name":"North West"},
  "E06000050": { "la_name":"Cheshire West and Chester", "region_code":"E12000002", "region_name":"North West"},
  "E06000051": { "la_name":"Shropshire", "region_code":"E12000005", "region_name":"West Midlands"},
  "E06000052": { "la_name":"Cornwall", "region_code":"E12000009", "region_name":"South West"},
  "E06000053": { "la_name":"Isles of Scilly", "region_code":"E12000009", "region_name":"South West"},
  "E06000054": { "la_name":"Wiltshire", "region_code":"E12000009", "region_name":"South West"},
  "E06000055": { "la_name":"Bedford", "region_code":"E12000006", "region_name":"East"},
  "E06000056": { "la_name":"Central Bedfordshire", "region_code":"E12000006", "region_name":"East"},
  "E07000004": { "la_name":"Aylesbury Vale", "region_code":"E12000008", "region_name":"South East"},
  "E07000005": { "la_name":"Chiltern", "region_code":"E12000008", "region_name":"South East"},
  "E07000006": { "la_name":"South Bucks", "region_code":"E12000008", "region_name":"South East"},
  "E07000007": { "la_name":"Wycombe", "region_code":"E12000008", "region_name":"South East"},
  "E07000008": { "la_name":"Cambridge", "region_code":"E12000006", "region_name":"East"},
  "E07000009": { "la_name":"East Cambridgeshire", "region_code":"E12000006", "region_name":"East"},
  "E07000010": { "la_name":"Fenland", "region_code":"E12000006", "region_name":"East"},
  "E07000011": { "la_name":"Huntingdonshire", "region_code":"E12000006", "region_name":"East"},
  "E07000012": { "la_name":"South Cambridgeshire", "region_code":"E12000006", "region_name":"East"},
  "E07000026": { "la_name":"Allerdale", "region_code":"E12000002", "region_name":"North West"},
  "E07000027": { "la_name":"Barrow-in-Furness", "region_code":"E12000002", "region_name":"North West"},
  "E07000028": { "la_name":"Carlisle", "region_code":"E12000002", "region_name":"North West"},
  "E07000029": { "la_name":"Copeland", "region_code":"E12000002", "region_name":"North West"},
  "E07000030": { "la_name":"Eden", "region_code":"E12000002", "region_name":"North West"},
  "E07000031": { "la_name":"South Lakeland", "region_code":"E12000002", "region_name":"North West"},
  "E07000032": { "la_name":"Amber Valley", "region_code":"E12000004", "region_name":"East Midlands"},
  "E07000033": { "la_name":"Bolsover", "region_code":"E12000004", "region_name":"East Midlands"},
  "E07000034": { "la_name":"Chesterfield", "region_code":"E12000004", "region_name":"East Midlands"},
  "E07000035": { "la_name":"Derbyshire Dales", "region_code":"E12000004", "region_name":"East Midlands"},
  "E07000036": { "la_name":"Erewash", "region_code":"E12000004", "region_name":"East Midlands"},
  "E07000037": { "la_name":"High Peak", "region_code":"E12000004", "region_name":"East Midlands"},
  "E07000038": { "la_name":"North East Derbyshire", "region_code":"E12000004", "region_name":"East Midlands"},
  "E07000039": { "la_name":"South Derbyshire", "region_code":"E12000004", "region_name":"East Midlands"},
  "E07000040": { "la_name":"East Devon", "region_code":"E12000009", "region_name":"South West"},
  "E07000041": { "la_name":"Exeter", "region_code":"E12000009", "region_name":"South West"},
  "E07000042": { "la_name":"Mid Devon", "region_code":"E12000009", "region_name":"South West"},
  "E07000043": { "la_name":"North Devon", "region_code":"E12000009", "region_name":"South West"},
  "E07000044": { "la_name":"South Hams", "region_code":"E12000009", "region_name":"South West"},
  "E07000045": { "la_name":"Teignbridge", "region_code":"E12000009", "region_name":"South West"},
  "E07000046": { "la_name":"Torridge", "region_code":"E12000009", "region_name":"South West"},
  "E07000047": { "la_name":"West Devon", "region_code":"E12000009", "region_name":"South West"},
  "E07000048": { "la_name":"Christchurch", "region_code":"E12000009", "region_name":"South West"},
  "E07000049": { "la_name":"East Dorset", "region_code":"E12000009", "region_name":"South West"},
  "E07000050": { "la_name":"North Dorset", "region_code":"E12000009", "region_name":"South West"},
  "E07000051": { "la_name":"Purbeck", "region_code":"E12000009", "region_name":"South West"},
  "E07000052": { "la_name":"West Dorset", "region_code":"E12000009", "region_name":"South West"},
  "E07000053": { "la_name":"Weymouth and Portland", "region_code":"E12000009", "region_name":"South West"},
  "E07000061": { "la_name":"Eastbourne", "region_code":"E12000008", "region_name":"South East"},
  "E07000062": { "la_name":"Hastings", "region_code":"E12000008", "region_name":"South East"},
  "E07000063": { "la_name":"Lewes", "region_code":"E12000008", "region_name":"South East"},
  "E07000064": { "la_name":"Rother", "region_code":"E12000008", "region_name":"South East"},
  "E07000065": { "la_name":"Wealden", "region_code":"E12000008", "region_name":"South East"},
  "E07000066": { "la_name":"Basildon", "region_code":"E12000006", "region_name":"East"},
  "E07000067": { "la_name":"Braintree", "region_code":"E12000006", "region_name":"East"},
  "E07000068": { "la_name":"Brentwood", "region_code":"E12000006", "region_name":"East"},
  "E07000069": { "la_name":"Castle Point", "region_code":"E12000006", "region_name":"East"},
  "E07000070": { "la_name":"Chelmsford", "region_code":"E12000006", "region_name":"East"},
  "E07000071": { "la_name":"Colchester", "region_code":"E12000006", "region_name":"East"},
  "E07000072": { "la_name":"Epping Forest", "region_code":"E12000006", "region_name":"East"},
  "E07000073": { "la_name":"Harlow", "region_code":"E12000006", "region_name":"East"},
  "E07000074": { "la_name":"Maldon", "region_code":"E12000006", "region_name":"East"},
  "E07000075": { "la_name":"Rochford", "region_code":"E12000006", "region_name":"East"},
  "E07000076": { "la_name":"Tendring", "region_code":"E12000006", "region_name":"East"},
  "E07000077": { "la_name":"Uttlesford", "region_code":"E12000006", "region_name":"East"},
  "E07000078": { "la_name":"Cheltenham", "region_code":"E12000009", "region_name":"South West"},
  "E07000079": { "la_name":"Cotswold", "region_code":"E12000009", "region_name":"South West"},
  "E07000080": { "la_name":"Forest of Dean", "region_code":"E12000009", "region_name":"South West"},
  "E07000081": { "la_name":"Gloucester", "region_code":"E12000009", "region_name":"South West"},
  "E07000082": { "la_name":"Stroud", "region_code":"E12000009", "region_name":"South West"},
  "E07000083": { "la_name":"Tewkesbury", "region_code":"E12000009", "region_name":"South West"},
  "E07000084": { "la_name":"Basingstoke and Deane", "region_code":"E12000008", "region_name":"South East"},
  "E07000085": { "la_name":"East Hampshire", "region_code":"E12000008", "region_name":"South East"},
  "E07000086": { "la_name":"Eastleigh", "region_code":"E12000008", "region_name":"South East"},
  "E07000087": { "la_name":"Fareham", "region_code":"E12000008", "region_name":"South East"},
  "E07000088": { "la_name":"Gosport", "region_code":"E12000008", "region_name":"South East"},
  "E07000089": { "la_name":"Hart", "region_code":"E12000008", "region_name":"South East"},
  "E07000090": { "la_name":"Havant", "region_code":"E12000008", "region_name":"South East"},
  "E07000091": { "la_name":"New Forest", "region_code":"E12000008", "region_name":"South East"},
  "E07000092": { "la_name":"Rushmoor", "region_code":"E12000008", "region_name":"South East"},
  "E07000093": { "la_name":"Test Valley", "region_code":"E12000008", "region_name":"South East"},
  "E07000094": { "la_name":"Winchester", "region_code":"E12000008", "region_name":"South East"},
  "E07000095": { "la_name":"Broxbourne", "region_code":"E12000006", "region_name":"East"},
  "E07000096": { "la_name":"Dacorum", "region_code":"E12000006", "region_name":"East"},
  "E07000097": { "la_name":"East Hertfordshire", "region_code":"E12000006", "region_name":"East"},
  "E07000242": { "la_name":"East Hertfordshire", "region_code":"E12000006", "region_name":"East"},
  "E07000098": { "la_name":"Hertsmere", "region_code":"E12000006", "region_name":"East"},
  "E07000099": { "la_name":"North Hertfordshire", "region_code":"E12000006", "region_name":"East"},
  "E07000101": { "la_name":"Stevenage", "region_code":"E12000006", "region_name":"East"},
  "E07000243": { "la_name":"Stevenage", "region_code":"E12000006", "region_name":"East"},
  "E07000102": { "la_name":"Three Rivers", "region_code":"E12000006", "region_name":"East"},
  "E07000103": { "la_name":"Watford", "region_code":"E12000006", "region_name":"East"},
  "E07000105": { "la_name":"Ashford", "region_code":"E12000008", "region_name":"South East"},
  "E07000106": { "la_name":"Canterbury", "region_code":"E12000008", "region_name":"South East"},
  "E07000107": { "la_name":"Dartford", "region_code":"E12000008", "region_name":"South East"},
  "E07000108": { "la_name":"Dover", "region_code":"E12000008", "region_name":"South East"},
  "E07000109": { "la_name":"Gravesham", "region_code":"E12000008", "region_name":"South East"},
  "E07000110": { "la_name":"Maidstone", "region_code":"E12000008", "region_name":"South East"},
  "E07000111": { "la_name":"Sevenoaks", "region_code":"E12000008", "region_name":"South East"},
  "E07000112": { "la_name":"Shepway", "region_code":"E12000008", "region_name":"South East"},
  "E07000113": { "la_name":"Swale", "region_code":"E12000008", "region_name":"South East"},
  "E07000114": { "la_name":"Thanet", "region_code":"E12000008", "region_name":"South East"},
  "E07000115": { "la_name":"Tonbridge and Malling", "region_code":"E12000008", "region_name":"South East"},
  "E07000116": { "la_name":"Tunbridge Wells", "region_code":"E12000008", "region_name":"South East"},
  "E07000117": { "la_name":"Burnley", "region_code":"E12000002", "region_name":"North West"},
  "E07000118": { "la_name":"Chorley", "region_code":"E12000002", "region_name":"North West"},
  "E07000119": { "la_name":"Fylde", "region_code":"E12000002", "region_name":"North West"},
  "E07000120": { "la_name":"Hyndburn", "region_code":"E12000002", "region_name":"North West"},
  "E07000121": { "la_name":"Lancaster", "region_code":"E12000002", "region_name":"North West"},
  "E07000122": { "la_name":"Pendle", "region_code":"E12000002", "region_name":"North West"},
  "E07000123": { "la_name":"Preston", "region_code":"E12000002", "region_name":"North West"},
  "E07000124": { "la_name":"Ribble Valley", "region_code":"E12000002", "region_name":"North West"},
  "E07000125": { "la_name":"Rossendale", "region_code":"E12000002", "region_name":"North West"},
  "E07000126": { "la_name":"South Ribble", "region_code":"E12000002", "region_name":"North West"},
  "E07000127": { "la_name":"West Lancashire", "region_code":"E12000002", "region_name":"North West"},
  "E07000128": { "la_name":"Wyre", "region_code":"E12000002", "region_name":"North West"},
  "E07000129": { "la_name":"Blaby", "region_code":"E12000004", "region_name":"East Midlands"},
  "E07000130": { "la_name":"Charnwood", "region_code":"E12000004", "region_name":"East Midlands"},
  "E07000131": { "la_name":"Harborough", "region_code":"E12000004", "region_name":"East Midlands"},
  "E07000132": { "la_name":"Hinckley and Bosworth", "region_code":"E12000004", "region_name":"East Midlands"},
  "E07000133": { "la_name":"Melton", "region_code":"E12000004", "region_name":"East Midlands"},
  "E07000134": { "la_name":"North West Leicestershire", "region_code":"E12000004", "region_name":"East Midlands"},
  "E07000135": { "la_name":"Oadby and Wigston", "region_code":"E12000004", "region_name":"East Midlands"},
  "E07000136": { "la_name":"Boston", "region_code":"E12000004", "region_name":"East Midlands"},
  "E07000137": { "la_name":"East Lindsey", "region_code":"E12000004", "region_name":"East Midlands"},
  "E07000138": { "la_name":"Lincoln", "region_code":"E12000004", "region_name":"East Midlands"},
  "E07000139": { "la_name":"North Kesteven", "region_code":"E12000004", "region_name":"East Midlands"},
  "E07000140": { "la_name":"South Holland", "region_code":"E12000004", "region_name":"East Midlands"},
  "E07000141": { "la_name":"South Kesteven", "region_code":"E12000004", "region_name":"East Midlands"},
  "E07000142": { "la_name":"West Lindsey", "region_code":"E12000004", "region_name":"East Midlands"},
  "E07000143": { "la_name":"Breckland", "region_code":"E12000006", "region_name":"East"},
  "E07000144": { "la_name":"Broadland", "region_code":"E12000006", "region_name":"East"},
  "E07000145": { "la_name":"Great Yarmouth", "region_code":"E12000006", "region_name":"East"},
  "E07000146": { "la_name":"King's Lynn and West Norfolk", "region_code":"E12000006", "region_name":"East"},
  "E07000147": { "la_name":"North Norfolk", "region_code":"E12000006", "region_name":"East"},
  "E07000148": { "la_name":"Norwich", "region_code":"E12000006", "region_name":"East"},
  "E07000149": { "la_name":"South Norfolk", "region_code":"E12000006", "region_name":"East"},
  "E07000150": { "la_name":"Corby", "region_code":"E12000004", "region_name":"East Midlands"},
  "E07000151": { "la_name":"Daventry", "region_code":"E12000004", "region_name":"East Midlands"},
  "E07000152": { "la_name":"East Northamptonshire", "region_code":"E12000004", "region_name":"East Midlands"},
  "E07000153": { "la_name":"Kettering", "region_code":"E12000004", "region_name":"East Midlands"},
  "E07000154": { "la_name":"Northampton", "region_code":"E12000004", "region_name":"East Midlands"},
  "E07000155": { "la_name":"South Northamptonshire", "region_code":"E12000004", "region_name":"East Midlands"},
  "E07000156": { "la_name":"Wellingborough", "region_code":"E12000004", "region_name":"East Midlands"},
  "E07000163": { "la_name":"Craven", "region_code":"E12000003", "region_name":"Yorkshire and The Humber"},
  "E07000164": { "la_name":"Hambleton", "region_code":"E12000003", "region_name":"Yorkshire and The Humber"},
  "E07000165": { "la_name":"Harrogate", "region_code":"E12000003", "region_name":"Yorkshire and The Humber"},
  "E07000166": { "la_name":"Richmondshire", "region_code":"E12000003", "region_name":"Yorkshire and The Humber"},
  "E07000167": { "la_name":"Ryedale", "region_code":"E12000003", "region_name":"Yorkshire and The Humber"},
  "E07000168": { "la_name":"Scarborough", "region_code":"E12000003", "region_name":"Yorkshire and The Humber"},
  "E07000169": { "la_name":"Selby", "region_code":"E12000003", "region_name":"Yorkshire and The Humber"},
  "E07000170": { "la_name":"Ashfield", "region_code":"E12000004", "region_name":"East Midlands"},
  "E07000171": { "la_name":"Bassetlaw", "region_code":"E12000004", "region_name":"East Midlands"},
  "E07000172": { "la_name":"Broxtowe", "region_code":"E12000004", "region_name":"East Midlands"},
  "E07000173": { "la_name":"Gedling", "region_code":"E12000004", "region_name":"East Midlands"},
  "E07000174": { "la_name":"Mansfield", "region_code":"E12000004", "region_name":"East Midlands"},
  "E07000175": { "la_name":"Newark and Sherwood", "region_code":"E12000004", "region_name":"East Midlands"},
  "E07000176": { "la_name":"Rushcliffe", "region_code":"E12000004", "region_name":"East Midlands"},
  "E07000177": { "la_name":"Cherwell", "region_code":"E12000008", "region_name":"South East"},
  "E07000178": { "la_name":"Oxford", "region_code":"E12000008", "region_name":"South East"},
  "E07000179": { "la_name":"South Oxfordshire", "region_code":"E12000008", "region_name":"South East"},
  "E07000180": { "la_name":"Vale of White Horse", "region_code":"E12000008", "region_name":"South East"},
  "E07000181": { "la_name":"West Oxfordshire", "region_code":"E12000008", "region_name":"South East"},
  "E07000187": { "la_name":"Mendip", "region_code":"E12000009", "region_name":"South West"},
  "E07000188": { "la_name":"Sedgemoor", "region_code":"E12000009", "region_name":"South West"},
  "E07000189": { "la_name":"South Somerset", "region_code":"E12000009", "region_name":"South West"},
  "E07000190": { "la_name":"Taunton Deane", "region_code":"E12000009", "region_name":"South West"},
  "E07000191": { "la_name":"West Somerset", "region_code":"E12000009", "region_name":"South West"},
  "E07000192": { "la_name":"Cannock Chase", "region_code":"E12000005", "region_name":"West Midlands"},
  "E07000193": { "la_name":"East Staffordshire", "region_code":"E12000005", "region_name":"West Midlands"},
  "E07000194": { "la_name":"Lichfield", "region_code":"E12000005", "region_name":"West Midlands"},
  "E07000195": { "la_name":"Newcastle-under-Lyme", "region_code":"E12000005", "region_name":"West Midlands"},
  "E07000196": { "la_name":"South Staffordshire", "region_code":"E12000005", "region_name":"West Midlands"},
  "E07000197": { "la_name":"Stafford", "region_code":"E12000005", "region_name":"West Midlands"},
  "E07000198": { "la_name":"Staffordshire Moorlands", "region_code":"E12000005", "region_name":"West Midlands"},
  "E07000199": { "la_name":"Tamworth", "region_code":"E12000005", "region_name":"West Midlands"},
  "E07000200": { "la_name":"Babergh", "region_code":"E12000006", "region_name":"East"},
  "E07000201": { "la_name":"Forest Heath", "region_code":"E12000006", "region_name":"East"},
  "E07000202": { "la_name":"Ipswich", "region_code":"E12000006", "region_name":"East"},
  "E07000203": { "la_name":"Mid Suffolk", "region_code":"E12000006", "region_name":"East"},
  "E07000204": { "la_name":"St Edmundsbury", "region_code":"E12000006", "region_name":"East"},
  "E07000205": { "la_name":"Suffolk Coastal", "region_code":"E12000006", "region_name":"East"},
  "E07000206": { "la_name":"Waveney", "region_code":"E12000006", "region_name":"East"},
  "E07000207": { "la_name":"Elmbridge", "region_code":"E12000008", "region_name":"South East"},
  "E07000208": { "la_name":"Epsom and Ewell", "region_code":"E12000008", "region_name":"South East"},
  "E07000209": { "la_name":"Guildford", "region_code":"E12000008", "region_name":"South East"},
  "E07000210": { "la_name":"Mole Valley", "region_code":"E12000008", "region_name":"South East"},
  "E07000211": { "la_name":"Reigate and Banstead", "region_code":"E12000008", "region_name":"South East"},
  "E07000212": { "la_name":"Runnymede", "region_code":"E12000008", "region_name":"South East"},
  "E07000213": { "la_name":"Spelthorne", "region_code":"E12000008", "region_name":"South East"},
  "E07000214": { "la_name":"Surrey Heath", "region_code":"E12000008", "region_name":"South East"},
  "E07000215": { "la_name":"Tandridge", "region_code":"E12000008", "region_name":"South East"},
  "E07000216": { "la_name":"Waverley", "region_code":"E12000008", "region_name":"South East"},
  "E07000217": { "la_name":"Woking", "region_code":"E12000008", "region_name":"South East"},
  "E07000218": { "la_name":"North Warwickshire", "region_code":"E12000005", "region_name":"West Midlands"},
  "E07000219": { "la_name":"Nuneaton and Bedworth", "region_code":"E12000005", "region_name":"West Midlands"},
  "E07000220": { "la_name":"Rugby", "region_code":"E12000005", "region_name":"West Midlands"},
  "E07000221": { "la_name":"Stratford-on-Avon", "region_code":"E12000005", "region_name":"West Midlands"},
  "E07000222": { "la_name":"Warwick", "region_code":"E12000005", "region_name":"West Midlands"},
  "E07000223": { "la_name":"Adur", "region_code":"E12000008", "region_name":"South East"},
  "E07000224": { "la_name":"Arun", "region_code":"E12000008", "region_name":"South East"},
  "E07000225": { "la_name":"Chichester", "region_code":"E12000008", "region_name":"South East"},
  "E07000226": { "la_name":"Crawley", "region_code":"E12000008", "region_name":"South East"},
  "E07000227": { "la_name":"Horsham", "region_code":"E12000008", "region_name":"South East"},
  "E07000228": { "la_name":"Mid Sussex", "region_code":"E12000008", "region_name":"South East"},
  "E07000229": { "la_name":"Worthing", "region_code":"E12000008", "region_name":"South East"},
  "E07000234": { "la_name":"Bromsgrove", "region_code":"E12000005", "region_name":"West Midlands"},
  "E07000235": { "la_name":"Malvern Hills", "region_code":"E12000005", "region_name":"West Midlands"},
  "E07000236": { "la_name":"Redditch", "region_code":"E12000005", "region_name":"West Midlands"},
  "E07000237": { "la_name":"Worcester", "region_code":"E12000005", "region_name":"West Midlands"},
  "E07000238": { "la_name":"Wychavon", "region_code":"E12000005", "region_name":"West Midlands"},
  "E07000239": { "la_name":"Wyre Forest", "region_code":"E12000005", "region_name":"West Midlands"},
  "E07000240": { "la_name":"St Albans", "region_code":"E12000006", "region_name":"East"},
  "E07000241": { "la_name":"Welwyn Hatfield", "region_code":"E12000006", "region_name":"East"},
  "E08000001": { "la_name":"Bolton", "region_code":"E12000002", "region_name":"North West"},
  "E08000002": { "la_name":"Bury", "region_code":"E12000002", "region_name":"North West"},
  "E08000003": { "la_name":"Manchester", "region_code":"E12000002", "region_name":"North West"},
  "E08000004": { "la_name":"Oldham", "region_code":"E12000002", "region_name":"North West"},
  "E08000005": { "la_name":"Rochdale", "region_code":"E12000002", "region_name":"North West"},
  "E08000006": { "la_name":"Salford", "region_code":"E12000002", "region_name":"North West"},
  "E08000007": { "la_name":"Stockport", "region_code":"E12000002", "region_name":"North West"},
  "E08000008": { "la_name":"Tameside", "region_code":"E12000002", "region_name":"North West"},
  "E08000009": { "la_name":"Trafford", "region_code":"E12000002", "region_name":"North West"},
  "E08000010": { "la_name":"Wigan", "region_code":"E12000002", "region_name":"North West"},
  "E08000011": { "la_name":"Knowsley", "region_code":"E12000002", "region_name":"North West"},
  "E08000012": { "la_name":"Liverpool", "region_code":"E12000002", "region_name":"North West"},
  "E08000013": { "la_name":"St. Helens", "region_code":"E12000002", "region_name":"North West"},
  "E08000014": { "la_name":"Sefton", "region_code":"E12000002", "region_name":"North West"},
  "E08000015": { "la_name":"Wirral", "region_code":"E12000002", "region_name":"North West"},
  "E08000016": { "la_name":"Barnsley", "region_code":"E12000003", "region_name":"Yorkshire and The Humber"},
  "E08000017": { "la_name":"Doncaster", "region_code":"E12000003", "region_name":"Yorkshire and The Humber"},
  "E08000018": { "la_name":"Rotherham", "region_code":"E12000003", "region_name":"Yorkshire and The Humber"},
  "E08000019": { "la_name":"Sheffield", "region_code":"E12000003", "region_name":"Yorkshire and The Humber"},
  "E08000020": { "la_name":"Gateshead", "region_code":"E12000001", "region_name":"North East"},
  "E08000037": { "la_name":"Gateshead", "region_code":"E12000001", "region_name":"North East"},
  "E08000021": { "la_name":"Newcastle upon Tyne", "region_code":"E12000001", "region_name":"North East"},
  "E08000022": { "la_name":"North Tyneside", "region_code":"E12000001", "region_name":"North East"},
  "E08000023": { "la_name":"South Tyneside", "region_code":"E12000001", "region_name":"North East"},
  "E08000024": { "la_name":"Sunderland", "region_code":"E12000001", "region_name":"North East"},
  "E08000025": { "la_name":"Birmingham", "region_code":"E12000005", "region_name":"West Midlands"},
  "E08000026": { "la_name":"Coventry", "region_code":"E12000005", "region_name":"West Midlands"},
  "E08000027": { "la_name":"Dudley", "region_code":"E12000005", "region_name":"West Midlands"},
  "E08000028": { "la_name":"Sandwell", "region_code":"E12000005", "region_name":"West Midlands"},
  "E08000029": { "la_name":"Solihull", "region_code":"E12000005", "region_name":"West Midlands"},
  "E08000030": { "la_name":"Walsall", "region_code":"E12000005", "region_name":"West Midlands"},
  "E08000031": { "la_name":"Wolverhampton", "region_code":"E12000005", "region_name":"West Midlands"},
  "E08000032": { "la_name":"Bradford", "region_code":"E12000003", "region_name":"Yorkshire and The Humber"},
  "E08000033": { "la_name":"Calderdale", "region_code":"E12000003", "region_name":"Yorkshire and The Humber"},
  "E08000034": { "la_name":"Kirklees", "region_code":"E12000003", "region_name":"Yorkshire and The Humber"},
  "E08000035": { "la_name":"Leeds", "region_code":"E12000003", "region_name":"Yorkshire and The Humber"},
  "E08000036": { "la_name":"Wakefield", "region_code":"E12000003", "region_name":"Yorkshire and The Humber"},
  "E09000001": { "la_name":"City of London", "region_code":"E12000007", "region_name":"London"},
  "E09000002": { "la_name":"Barking and Dagenham", "region_code":"E12000007", "region_name":"London"},
  "E09000003": { "la_name":"Barnet", "region_code":"E12000007", "region_name":"London"},
  "E09000004": { "la_name":"Bexley", "region_code":"E12000007", "region_name":"London"},
  "E09000005": { "la_name":"Brent", "region_code":"E12000007", "region_name":"London"},
  "E09000006": { "la_name":"Bromley", "region_code":"E12000007", "region_name":"London"},
  "E09000007": { "la_name":"Camden", "region_code":"E12000007", "region_name":"London"},
  "E09000008": { "la_name":"Croydon", "region_code":"E12000007", "region_name":"London"},
  "E09000009": { "la_name":"Ealing", "region_code":"E12000007", "region_name":"London"},
  "E09000010": { "la_name":"Enfield", "region_code":"E12000007", "region_name":"London"},
  "E09000011": { "la_name":"Greenwich", "region_code":"E12000007", "region_name":"London"},
  "E09000012": { "la_name":"Hackney", "region_code":"E12000007", "region_name":"London"},
  "E09000013": { "la_name":"Hammersmith and Fulham", "region_code":"E12000007", "region_name":"London"},
  "E09000014": { "la_name":"Haringey", "region_code":"E12000007", "region_name":"London"},
  "E09000015": { "la_name":"Harrow", "region_code":"E12000007", "region_name":"London"},
  "E09000016": { "la_name":"Havering", "region_code":"E12000007", "region_name":"London"},
  "E09000017": { "la_name":"Hillingdon", "region_code":"E12000007", "region_name":"London"},
  "E09000018": { "la_name":"Hounslow", "region_code":"E12000007", "region_name":"London"},
  "E09000019": { "la_name":"Islington", "region_code":"E12000007", "region_name":"London"},
  "E09000020": { "la_name":"Kensington and Chelsea", "region_code":"E12000007", "region_name":"London"},
  "E09000021": { "la_name":"Kingston upon Thames", "region_code":"E12000007", "region_name":"London"},
  "E09000022": { "la_name":"Lambeth", "region_code":"E12000007", "region_name":"London"},
  "E09000023": { "la_name":"Lewisham", "region_code":"E12000007", "region_name":"London"},
  "E09000024": { "la_name":"Merton", "region_code":"E12000007", "region_name":"London"},
  "E09000025": { "la_name":"Newham", "region_code":"E12000007", "region_name":"London"},
  "E09000026": { "la_name":"Redbridge", "region_code":"E12000007", "region_name":"London"},
  "E09000027": { "la_name":"Richmond upon Thames", "region_code":"E12000007", "region_name":"London"},
  "E09000028": { "la_name":"Southwark", "region_code":"E12000007", "region_name":"London"},
  "E09000029": { "la_name":"Sutton", "region_code":"E12000007", "region_name":"London"},
  "E09000030": { "la_name":"Tower Hamlets", "region_code":"E12000007", "region_name":"London"},
  "E09000031": { "la_name":"Waltham Forest", "region_code":"E12000007", "region_name":"London"},
  "E09000032": { "la_name":"Wandsworth", "region_code":"E12000007", "region_name":"London"},
  "E09000033": { "la_name":"Westminster", "region_code":"E12000007", "region_name":"London"},
  "W06000001": { "la_name":"Isle of Anglesey", "region_code":"W92000004", "region_name":"Wales"},
  "W06000002": { "la_name":"Gwynedd", "region_code":"W92000004", "region_name":"Wales"},
  "W06000003": { "la_name":"Conwy", "region_code":"W92000004", "region_name":"Wales"},
  "W06000004": { "la_name":"Denbighshire", "region_code":"W92000004", "region_name":"Wales"},
  "W06000005": { "la_name":"Flintshire", "region_code":"W92000004", "region_name":"Wales"},
  "W06000006": { "la_name":"Wrexham", "region_code":"W92000004", "region_name":"Wales"},
  "W06000008": { "la_name":"Ceredigion", "region_code":"W92000004", "region_name":"Wales"},
  "W06000009": { "la_name":"Pembrokeshire", "region_code":"W92000004", "region_name":"Wales"},
  "W06000010": { "la_name":"Carmarthenshire", "region_code":"W92000004", "region_name":"Wales"},
  "W06000011": { "la_name":"Swansea", "region_code":"W92000004", "region_name":"Wales"},
  "W06000012": { "la_name":"Neath Port Talbot", "region_code":"W92000004", "region_name":"Wales"},
  "W06000013": { "la_name":"Bridgend", "region_code":"W92000004", "region_name":"Wales"},
  "W06000014": { "la_name":"The Vale of Glamorgan", "region_code":"W92000004", "region_name":"Wales"},
  "W06000015": { "la_name":"Cardiff", "region_code":"W92000004", "region_name":"Wales"},
  "W06000016": { "la_name":"Rhondda Cynon Taf", "region_code":"W92000004", "region_name":"Wales"},
  "W06000018": { "la_name":"Caerphilly", "region_code":"W92000004", "region_name":"Wales"},
  "W06000019": { "la_name":"Blaenau Gwent", "region_code":"W92000004", "region_name":"Wales"},
  "W06000020": { "la_name":"Torfaen", "region_code":"W92000004", "region_name":"Wales"},
  "W06000021": { "la_name":"Monmouthshire", "region_code":"W92000004", "region_name":"Wales"},
  "W06000022": { "la_name":"Newport", "region_code":"W92000004", "region_name":"Wales"},
  "W06000023": { "la_name":"Powys", "region_code":"W92000004", "region_name":"Wales"},
  "W06000024": { "la_name":"Merthyr Tydfil", "region_code":"W92000004", "region_name":"Wales"}
}